
<!DOCTYPE Metadata [
  <!ENTITY % BIND_VALUES PUBLIC "OLAP BIND VALUES" "OLAP METADATA">
  %BIND_VALUES;
  ]>
<Metadata
  Version="2.1"
  MinimumDatabaseVersion="12.2.0.0">
  <StandardDimension
    Name="FINAL_JOBS"
    ETViewName="FINAL_JOBS_VIEW"
    ETKeyColumnName="DIM_KEY"
    ETLevelColumnName="LEVEL_NAME"
    ETMemberTypeColumnName="MEMBER_TYPE"
    ETDimensionOrderColumnName="DIM_ORDER"
    ETHierarchyOrderColumnName="HIER_ORDER"
    DefaultHierarchy="FINAL_HRC_JOB"
    ValueDescriptionAttribute="LONG_DESCRIPTION"
    ShortValueDescriptionAttribute="SHORT_DESCRIPTION">
    <Hierarchy>
      <LevelHierarchy
        IsSkipLevel="False"
        IsRagged="False"
        IsSnowflake="False"
        Name="FINAL_HRC_JOB"
        ETParentColumnName="PARENT"
        ETDepthColumnName="DEPTH"
        ETViewName="FINAL_JOBS_FINAL_HRC_JOB_VIEW">
        <Description
          Type="LongDescription"
          Language="AMERICAN"
          Value="Final HRC Job">
        </Description>
        <Description
          Type="ShortDescription"
          Language="AMERICAN"
          Value="Final HRC Job">
        </Description>
        <Description
          Type="Description"
          Language="AMERICAN"
          Value="Final HRC Job">
        </Description>
        <HierarchyLevel
          DimensionLevel="ALL_JOBS">
          <HierarchyLevelMap
            KeyExpression="&apos;ALL_JOBS&apos;"
            Query="DIMJOBS">
            <AttributeMap
              Name="LONG_DESCRIPTION"
              Attribute="LONG_DESCRIPTION"
              Expression="&apos;All Jobs&apos;">
            </AttributeMap>
            <AttributeMap
              Name="ALL_JOBS_LONG_DESCRIPTION"
              Attribute="ALL_JOBS_LONG_DESCRIPTION"
              Expression="&apos;All Jobs&apos;">
            </AttributeMap>
            <AttributeMap
              Name="SHORT_DESCRIPTION"
              Attribute="SHORT_DESCRIPTION"
              Expression="&apos;All Jobs&apos;">
            </AttributeMap>
            <AttributeMap
              Name="ALL_JOBS_SHORT_DESCRIPTION"
              Attribute="ALL_JOBS_SHORT_DESCRIPTION"
              Expression="&apos;All Jobs&apos;">
            </AttributeMap>
            <AttributeMap
              Name="FINAL_JOBS_ALL_JOBS_ID"
              Attribute="FINAL_JOBS_ALL_JOBS_ID"
              Expression="&apos;ALL_JOBS&apos;">
            </AttributeMap>
          </HierarchyLevelMap>
        </HierarchyLevel>
        <HierarchyLevel
          DimensionLevel="SALARY_CATEGORY">
          <HierarchyLevelMap
            KeyExpression="DIMJOBS.SALARYCATEGORY"
            Query="DIMJOBS">
            <AttributeMap
              Name="LONG_DESCRIPTION"
              Attribute="LONG_DESCRIPTION"
              Expression="DIMJOBS.SALARYCATEGORY">
            </AttributeMap>
            <AttributeMap
              Name="SALARY_CATEGORY_LONG_DESCRIP"
              Attribute="SALARY_CATEGORY_LONG_DESCRIP"
              Expression="DIMJOBS.SALARYCATEGORY">
            </AttributeMap>
            <AttributeMap
              Name="SHORT_DESCRIPTION"
              Attribute="SHORT_DESCRIPTION"
              Expression="DIMJOBS.SALARYCATEGORY">
            </AttributeMap>
            <AttributeMap
              Name="SALARY_CATEGORY_SHORT_DESCRI"
              Attribute="SALARY_CATEGORY_SHORT_DESCRI"
              Expression="DIMJOBS.SALARYCATEGORY">
            </AttributeMap>
            <AttributeMap
              Name="FINAL_JOBS_SALARY_CATEGORY_ID"
              Attribute="FINAL_JOBS_SALARY_CATEGORY_ID"
              Expression="DIMJOBS.SALARYCATEGORY">
            </AttributeMap>
          </HierarchyLevelMap>
        </HierarchyLevel>
        <HierarchyLevel
          DimensionLevel="JOB">
          <HierarchyLevelMap
            KeyExpression="DIMJOBS.JOBKEY"
            Query="DIMJOBS">
            <AttributeMap
              Name="LONG_DESCRIPTION"
              Attribute="LONG_DESCRIPTION"
              Expression="DIMJOBS.JOBTITLE">
            </AttributeMap>
            <AttributeMap
              Name="JOB_LONG_DESCRIPTION"
              Attribute="JOB_LONG_DESCRIPTION"
              Expression="DIMJOBS.JOBTITLE">
            </AttributeMap>
            <AttributeMap
              Name="SHORT_DESCRIPTION"
              Attribute="SHORT_DESCRIPTION"
              Expression="DIMJOBS.JOBTITLE">
            </AttributeMap>
            <AttributeMap
              Name="JOB_SHORT_DESCRIPTION"
              Attribute="JOB_SHORT_DESCRIPTION"
              Expression="DIMJOBS.JOBTITLE">
            </AttributeMap>
            <AttributeMap
              Name="FINAL_JOBS_JOB_ID"
              Attribute="FINAL_JOBS_JOB_ID"
              Expression="DIMJOBS.JOBKEY">
            </AttributeMap>
          </HierarchyLevelMap>
        </HierarchyLevel>
      </LevelHierarchy>
    </Hierarchy>
    <DimensionLevel
      Name="ALL_JOBS"
      ETKeyColumnName="ALL_JOBS">
      <Description
        Type="LongDescription"
        Language="AMERICAN"
        Value="All Jobs">
      </Description>
      <Description
        Type="ShortDescription"
        Language="AMERICAN"
        Value="All Jobs">
      </Description>
      <Description
        Type="Description"
        Language="AMERICAN"
        Value="All Jobs">
      </Description>
      <UniqueKeyAttribute
        Name="FINAL_JOBS_ALL_JOBS_ID"/>
      <VisibleAttribute
        Name="ALL_JOBS_LONG_DESCRIPTION"/>
      <VisibleAttribute
        Name="ALL_JOBS_SHORT_DESCRIPTION"/>
    </DimensionLevel>
    <DimensionLevel
      Name="SALARY_CATEGORY"
      ETKeyColumnName="SALARY_CATEGORY">
      <Description
        Type="LongDescription"
        Language="AMERICAN"
        Value="Salary Category">
      </Description>
      <Description
        Type="ShortDescription"
        Language="AMERICAN"
        Value="Salary Category">
      </Description>
      <Description
        Type="Description"
        Language="AMERICAN"
        Value="Salary Category">
      </Description>
      <UniqueKeyAttribute
        Name="FINAL_JOBS_SALARY_CATEGORY_ID"/>
      <VisibleAttribute
        Name="SALARY_CATEGORY_LONG_DESCRIP"/>
      <VisibleAttribute
        Name="SALARY_CATEGORY_SHORT_DESCRI"/>
    </DimensionLevel>
    <DimensionLevel
      Name="JOB"
      ETKeyColumnName="JOB">
      <Description
        Type="LongDescription"
        Language="AMERICAN"
        Value="Job">
      </Description>
      <Description
        Type="ShortDescription"
        Language="AMERICAN"
        Value="Job">
      </Description>
      <Description
        Type="Description"
        Language="AMERICAN"
        Value="Job">
      </Description>
      <UniqueKeyAttribute
        Name="FINAL_JOBS_JOB_ID"/>
      <VisibleAttribute
        Name="JOB_LONG_DESCRIPTION"/>
      <VisibleAttribute
        Name="JOB_SHORT_DESCRIPTION"/>
    </DimensionLevel>
    <Attribute>
      <BaseAttribute
        SQLDataType="VARCHAR2(256 BYTE)"
        AllowAutoDataTypeChange="True"
        ETAttributeColumnName="LONG_DESCRIPTION"
        IsMultiLingual="False"
        PopulateLineage="False"
        IsLoopMask="False"
        IsVisibleForAll="True"
        IsLevelUnique="False"
        Name="LONG_DESCRIPTION">
        <Classification
          Value="STAR"/>
        <Description
          Type="ShortDescription"
          Language="AMERICAN"
          Value="Long Description">
        </Description>
        <Description
          Type="LongDescription"
          Language="AMERICAN"
          Value="Long Description">
        </Description>
        <Description
          Type="Description"
          Language="AMERICAN"
          Value="Long Description">
        </Description>
      </BaseAttribute>
    </Attribute>
    <Attribute>
      <BaseAttribute
        SQLDataType="VARCHAR2(256 BYTE)"
        AllowAutoDataTypeChange="True"
        ETAttributeColumnName="SHORT_DESCRIPTION"
        IsMultiLingual="False"
        PopulateLineage="False"
        IsLoopMask="False"
        IsVisibleForAll="True"
        IsLevelUnique="False"
        Name="SHORT_DESCRIPTION">
        <Classification
          Value="STAR"/>
        <Description
          Type="ShortDescription"
          Language="AMERICAN"
          Value="Short Description">
        </Description>
        <Description
          Type="LongDescription"
          Language="AMERICAN"
          Value="Short Description">
        </Description>
        <Description
          Type="Description"
          Language="AMERICAN"
          Value="Short Description">
        </Description>
      </BaseAttribute>
    </Attribute>
    <Attribute>
      <BaseAttribute
        SQLDataType="CHAR(8 BYTE)"
        AllowAutoDataTypeChange="True"
        ETAttributeColumnName="ALL_JOBS_LONG_DESCRIPTION"
        IsMultiLingual="False"
        PopulateLineage="True"
        AttributeGroupName="LONG_DESCRIPTION"
        IsLoopMask="False"
        IsVisibleForAll="False"
        IsLevelUnique="False"
        Name="ALL_JOBS_LONG_DESCRIPTION">
        <Description
          Type="LongDescription"
          Language="AMERICAN"
          Value="All Jobs Long Description">
        </Description>
        <Description
          Type="ShortDescription"
          Language="AMERICAN"
          Value="All Jobs Long Description">
        </Description>
        <Description
          Type="Description"
          Language="AMERICAN"
          Value="All Jobs Long Description">
        </Description>
      </BaseAttribute>
    </Attribute>
    <Attribute>
      <BaseAttribute
        SQLDataType="CHAR(8 BYTE)"
        AllowAutoDataTypeChange="True"
        ETAttributeColumnName="ALL_JOBS_SHORT_DESCRIPTION"
        IsMultiLingual="False"
        PopulateLineage="True"
        AttributeGroupName="SHORT_DESCRIPTION"
        IsLoopMask="False"
        IsVisibleForAll="False"
        IsLevelUnique="False"
        Name="ALL_JOBS_SHORT_DESCRIPTION">
        <Description
          Type="LongDescription"
          Language="AMERICAN"
          Value="All Jobs Short Description">
        </Description>
        <Description
          Type="ShortDescription"
          Language="AMERICAN"
          Value="All Jobs Short Description">
        </Description>
        <Description
          Type="Description"
          Language="AMERICAN"
          Value="All Jobs Short Description">
        </Description>
      </BaseAttribute>
    </Attribute>
    <Attribute>
      <BaseAttribute
        SQLDataType="NVARCHAR2(25)"
        AllowAutoDataTypeChange="True"
        ETAttributeColumnName="SALARY_CATEGORY_LONG_DESCRIP"
        IsMultiLingual="False"
        PopulateLineage="True"
        AttributeGroupName="LONG_DESCRIPTION"
        IsLoopMask="False"
        IsVisibleForAll="False"
        IsLevelUnique="False"
        Name="SALARY_CATEGORY_LONG_DESCRIP">
        <Description
          Type="LongDescription"
          Language="AMERICAN"
          Value="Salary Category Long Description">
        </Description>
        <Description
          Type="ShortDescription"
          Language="AMERICAN"
          Value="Salary Category Long Description">
        </Description>
        <Description
          Type="Description"
          Language="AMERICAN"
          Value="Salary Category Long Description">
        </Description>
      </BaseAttribute>
    </Attribute>
    <Attribute>
      <BaseAttribute
        SQLDataType="NVARCHAR2(25)"
        AllowAutoDataTypeChange="True"
        ETAttributeColumnName="SALARY_CATEGORY_SHORT_DESCRI"
        IsMultiLingual="False"
        PopulateLineage="True"
        AttributeGroupName="SHORT_DESCRIPTION"
        IsLoopMask="False"
        IsVisibleForAll="False"
        IsLevelUnique="False"
        Name="SALARY_CATEGORY_SHORT_DESCRI">
        <Description
          Type="LongDescription"
          Language="AMERICAN"
          Value="Salary Category Short Description">
        </Description>
        <Description
          Type="ShortDescription"
          Language="AMERICAN"
          Value="Salary Category Short Description">
        </Description>
        <Description
          Type="Description"
          Language="AMERICAN"
          Value="Salary Category Short Description">
        </Description>
      </BaseAttribute>
    </Attribute>
    <Attribute>
      <BaseAttribute
        SQLDataType="NVARCHAR2(35)"
        AllowAutoDataTypeChange="True"
        ETAttributeColumnName="JOB_LONG_DESCRIPTION"
        IsMultiLingual="False"
        PopulateLineage="True"
        AttributeGroupName="LONG_DESCRIPTION"
        IsLoopMask="False"
        IsVisibleForAll="False"
        IsLevelUnique="False"
        Name="JOB_LONG_DESCRIPTION">
        <Description
          Type="LongDescription"
          Language="AMERICAN"
          Value="Job Long Description">
        </Description>
        <Description
          Type="ShortDescription"
          Language="AMERICAN"
          Value="Job Long Description">
        </Description>
        <Description
          Type="Description"
          Language="AMERICAN"
          Value="Job Long Description">
        </Description>
      </BaseAttribute>
    </Attribute>
    <Attribute>
      <BaseAttribute
        SQLDataType="NVARCHAR2(35)"
        AllowAutoDataTypeChange="True"
        ETAttributeColumnName="JOB_SHORT_DESCRIPTION"
        IsMultiLingual="False"
        PopulateLineage="True"
        AttributeGroupName="SHORT_DESCRIPTION"
        IsLoopMask="False"
        IsVisibleForAll="False"
        IsLevelUnique="False"
        Name="JOB_SHORT_DESCRIPTION">
        <Description
          Type="LongDescription"
          Language="AMERICAN"
          Value="Job Short Description">
        </Description>
        <Description
          Type="ShortDescription"
          Language="AMERICAN"
          Value="Job Short Description">
        </Description>
        <Description
          Type="Description"
          Language="AMERICAN"
          Value="Job Short Description">
        </Description>
      </BaseAttribute>
    </Attribute>
    <Attribute>
      <BaseAttribute
        SQLDataType="VARCHAR2(60 CHAR)"
        AllowAutoDataTypeChange="False"
        ETAttributeColumnName="FINAL_JOBS_ALL_JOBS_ID"
        IsMultiLingual="False"
        PopulateLineage="False"
        IsLoopMask="False"
        IsVisibleForAll="False"
        IsLevelUnique="False"
        Name="FINAL_JOBS_ALL_JOBS_ID">
      </BaseAttribute>
    </Attribute>
    <Attribute>
      <BaseAttribute
        SQLDataType="NVARCHAR2(25)"
        AllowAutoDataTypeChange="True"
        ETAttributeColumnName="FINAL_JOBS_SALARY_CATEGORY_ID"
        IsMultiLingual="False"
        PopulateLineage="False"
        IsLoopMask="False"
        IsVisibleForAll="False"
        IsLevelUnique="False"
        Name="FINAL_JOBS_SALARY_CATEGORY_ID">
        <Description
          Type="ShortDescription"
          Language="AMERICAN"
          Value="Salary Category">
        </Description>
        <Description
          Type="Description"
          Language="AMERICAN"
          Value="Salary Category">
        </Description>
        <Description
          Type="LongDescription"
          Language="AMERICAN"
          Value="Salary Category">
        </Description>
      </BaseAttribute>
    </Attribute>
    <Attribute>
      <BaseAttribute
        SQLDataType="NUMBER(10, 0)"
        AllowAutoDataTypeChange="True"
        ETAttributeColumnName="FINAL_JOBS_JOB_ID"
        IsMultiLingual="False"
        PopulateLineage="False"
        IsLoopMask="False"
        IsVisibleForAll="False"
        IsLevelUnique="False"
        Name="FINAL_JOBS_JOB_ID">
        <Description
          Type="ShortDescription"
          Language="AMERICAN"
          Value="Job">
        </Description>
        <Description
          Type="Description"
          Language="AMERICAN"
          Value="Job">
        </Description>
        <Description
          Type="LongDescription"
          Language="AMERICAN"
          Value="Job">
        </Description>
      </BaseAttribute>
    </Attribute>
    <Organization>
      <AWPrimaryDimensionOrganization
        MVOption="NONE"
        HierarchyConsistencyRule="STAR_CONSISTENT"
        AddUniqueKeyPrefix="False"
        AW="&AW_NAME;">
        <MVCreationOptions
          RefreshOn="DEMAND"
          RefreshType="COMPLETE"
          UsingConstraintsClause="TRUSTED">
        </MVCreationOptions>
        <AttributeOrganization
          CreateIndex="False"
          Attribute="LONG_DESCRIPTION">
        </AttributeOrganization>
        <AttributeOrganization
          CreateIndex="False"
          Attribute="SHORT_DESCRIPTION">
        </AttributeOrganization>
        <AttributeOrganization
          CreateIndex="False"
          Attribute="ALL_JOBS_LONG_DESCRIPTION">
        </AttributeOrganization>
        <AttributeOrganization
          CreateIndex="False"
          Attribute="ALL_JOBS_SHORT_DESCRIPTION">
        </AttributeOrganization>
        <AttributeOrganization
          CreateIndex="False"
          Attribute="SALARY_CATEGORY_LONG_DESCRIP">
        </AttributeOrganization>
        <AttributeOrganization
          CreateIndex="False"
          Attribute="SALARY_CATEGORY_SHORT_DESCRI">
        </AttributeOrganization>
        <AttributeOrganization
          CreateIndex="False"
          Attribute="JOB_LONG_DESCRIPTION">
        </AttributeOrganization>
        <AttributeOrganization
          CreateIndex="False"
          Attribute="JOB_SHORT_DESCRIPTION">
        </AttributeOrganization>
        <AttributeOrganization
          CreateIndex="False"
          Attribute="FINAL_JOBS_ALL_JOBS_ID">
        </AttributeOrganization>
        <AttributeOrganization
          CreateIndex="False"
          Attribute="FINAL_JOBS_SALARY_CATEGORY_ID">
        </AttributeOrganization>
        <AttributeOrganization
          CreateIndex="False"
          Attribute="FINAL_JOBS_JOB_ID">
        </AttributeOrganization>
        <DefaultBuild>
          <![CDATA[BUILD SPEC SYS_DEFAULT
(
  LOAD, 
  COMPILE
)]]>
        </DefaultBuild>
      </AWPrimaryDimensionOrganization>
    </Organization>
    <Description
      Type="LongDescription"
      Language="AMERICAN"
      Value="Final Jobs">
    </Description>
    <Description
      Type="ShortDescription"
      Language="AMERICAN"
      Value="Final Jobs">
    </Description>
    <Description
      Type="Description"
      Language="AMERICAN"
      Value="Final Jobs">
    </Description>
  </StandardDimension>
</Metadata>
<!--Generated by the Oracle Analytic Workspace Manager-->